customer_analysis/__init__.py
customer_analysis/__main__.py
customer_analysis/main.py
value_counts_by_csv_file_cu_homework-0.1.0.dist-info/METADATA
value_counts_by_csv_file_cu_homework-0.1.0.dist-info/WHEEL
value_counts_by_csv_file_cu_homework-0.1.0.dist-info/top_level.txt
value_counts_by_csv_file_cu_homework-0.1.0.dist-info/RECORD
