Metadata-Version: 2.1
Name: value-counts-by-csv-file-cu-homework
Version: 0.1.0
Summary: Отчёт по csv file
Author-email: Matvey Perminov <mectu@mail.ru>
License: MIT
Requires-Python: >=3.12
Requires-Dist: numpy >=2.1.2
Requires-Dist: pandas >=2.2.3
